gabriel_puc_csv_converter/__init__.py
gabriel_puc_csv_converter/_tests/conftest.py
gabriel_puc_csv_converter/_tests/test_unit_converter.py
gabriel_puc_csv_converter/_tests/test_unit_main.py
gabriel_puc_csv_converter/converter.py
gabriel_puc_csv_converter/main.py
gabriel_puc_csv_converter-0.2.0.dist-info/entry_points.txt
gabriel_puc_csv_converter-0.2.0.dist-info/LICENSE
gabriel_puc_csv_converter-0.2.0.dist-info/WHEEL
gabriel_puc_csv_converter-0.2.0.dist-info/METADATA
gabriel_puc_csv_converter-0.2.0.dist-info/RECORD
