Metadata-Version: 2.1
Name: gabriel-puc-csv-converter
Version: 0.2.0
Summary: Convert csv to json. Publishing only for learning purposes at PUC.
Home-page: https://github.com/gabgovar/csv_converter
License: MIT
Author: Gabriel Vargas
Author-email: gabrielvargas@usp.br
Requires-Python: >=3.9,<4.0
Classifier: License :: OSI Approved :: MIT License
Classifier: Programming Language :: Python :: 3
Classifier: Programming Language :: Python :: 3.10
Classifier: Programming Language :: Python :: 3.9
Requires-Dist: click (>=8.0.1,<9.0.0)
